phylodm-3.2.0.dist-info/METADATA
phylodm-3.2.0.dist-info/WHEEL
phylodm-3.2.0.dist-info/licenses/LICENSE
phylodm/__init__.py
phylodm/py.typed
phylodm/pdm.cpython-38-darwin.so
phylodm-3.2.0.dist-info/RECORD
