Metadata-Version: 2.3
Name: phylodm
Version: 3.2.0
Classifier: Development Status :: 5 - Production/Stable
Classifier: Intended Audience :: Science/Research
Classifier: License :: OSI Approved :: GNU General Public License v3 (GPLv3)
Classifier: Natural Language :: English
Classifier: Operating System :: OS Independent
Classifier: Programming Language :: Python :: 3.8
Classifier: Programming Language :: Python :: 3.9
Classifier: Programming Language :: Python :: 3.10
Classifier: Programming Language :: Python :: 3.11
Classifier: Programming Language :: Python :: 3.12
Classifier: Programming Language :: Rust
Classifier: Topic :: Scientific/Engineering :: Bio-Informatics
Requires-Dist: dendropy
Requires-Dist: numpy
License-File: LICENSE
Summary: Efficient calculation of phylogenetic distance matrices.
Keywords: phylogenetic,distance,matrix,symmetric
Author: Aaron Mussig <aaronmussig@gmail.com>
Author-email: Aaron Mussig <aaronmussig@gmail.com>
License: GPL-3.0
Requires-Python: >=3.8
Project-URL: Homepage, https://github.com/aaronmussig/PhyloDM
Project-URL: Documentation, https://github.com/aaronmussig/PhyloDM
Project-URL: Repository, https://github.com/aaronmussig/PhyloDM
Project-URL: Issues, https://github.com/aaronmussig/PhyloDM/issues
Project-URL: Changelog, https://github.com/aaronmussig/PhyloDM/blob/main/CHANGELOG.md
